[
    {
        "sku":  "SKU-619879",
        "published":  true,
        "order":  1,
        "tags":  [

                 ],
        "translations":  [
                             {
                                 "lang":  "ru",
                                 "description":  "# # BITACO BLACK TEA – Колумбийское Сокровище Анд  # BITACO BLACK TEA – Колумбийское Сокровище Анд  **1. Классификация и Происхождение:**  *   **Тип:** Черный чай (ортодоксальный, цельнолистовой). В зависимости от грейда может варьироваться степень измельчения листа. *   **Категория:** Органический чай, высокогорный чай, чай терруарного происхождения (Single Origin). *   **Происхождение:** Колумбия, Анды, долина реки Битако, муниципалитет Ла-Кумбре, департамент Валье-дель-Каука. Выращивается и п",
                                 "name":  "bitaco-black-tea",
                                 "seoName":  "bitaco-black-tea"
                             }
                         ],
        "specs":  [
                      {
                          "option":  "SPEC-TYPE-GREEN",
                          "type":  "Option",
                          "showOnPage":  true,
                          "attribute":  "SPEC-TEA-TYPE",
                          "order":  1
                      }
                  ],
        "code":  "TEA-COL-BITACOBLACKT",
        "catalog":  "CATALOG-AMERICAS",
        "origins":  [

                    ]
    },
    {
        "sku":  "SKU-100314",
        "published":  true,
        "order":  1,
        "tags":  [

                 ],
        "translations":  [
                             {
                                 "lang":  "ru",
                                 "description":  "# # BITACO \u0027ESPECIAL\u0027 WHITE TEA  # BITACO \u0027ESPECIAL\u0027 WHITE TEA  **1. Классификация и Происхождение:**  *   **Тип:** Белый чай (White Tea). Хотя в исходном описании упоминается близость к китайским сортам типа Бай Хао Инь Чжэнь («Серебряные иглы»), его уникальные характеристики и происхождение выделяют его. *   **Категория:** Органический высокогорный белый чай. *   **Происхождение:** Плантация Битако (Bitaco), расположенная в долине Каука, Анды, Колумбия. Чай выращивается на высоте 1800–2050 мет",
                                 "name":  "bitaco-especial-white-tea",
                                 "seoName":  "bitaco-especial-white-tea"
                             }
                         ],
        "specs":  [
                      {
                          "option":  "SPEC-TYPE-WHITE",
                          "type":  "Option",
                          "showOnPage":  true,
                          "attribute":  "SPEC-TEA-TYPE",
                          "order":  1
                      }
                  ],
        "code":  "TEA-COL-BITACOESPECI",
        "catalog":  "CATALOG-AMERICAS",
        "origins":  [

                    ]
    },
    {
        "sku":  "SKU-876214",
        "published":  true,
        "order":  1,
        "tags":  [

                 ],
        "translations":  [
                             {
                                 "lang":  "ru",
                                 "description":  "# # BITACO \u0027GOLDEN TIPPY\u0027 BLACK TEA  # BITACO \u0027GOLDEN TIPPY\u0027 BLACK TEA  **1. Классификация и Происхождение:**  *   **Тип:** Черный чай (полностью ферментированный). *   **Категория:** Высокогорный органический чай, single estate (произведенный в одном хозяйстве). *   **Происхождение:** Плантация Битако (Bitaco Unique Colombian Tea), расположенная в Андах, департамент Валье-дель-Каука, Колумбия. *   **Географические координаты:** Приблизительно 3°34\u0027 северной широты, 76°37\u0027 западной долготы. Уник",
                                 "name":  "bitaco-golden-tippy-black-tea",
                                 "seoName":  "bitaco-golden-tippy-black-tea"
                             }
                         ],
        "specs":  [
                      {
                          "option":  "SPEC-TYPE-GREEN",
                          "type":  "Option",
                          "showOnPage":  true,
                          "attribute":  "SPEC-TEA-TYPE",
                          "order":  1
                      }
                  ],
        "code":  "TEA-COL-BITACOGOLDEN",
        "catalog":  "CATALOG-AMERICAS",
        "origins":  [

                    ]
    },
    {
        "sku":  "SKU-625159",
        "published":  true,
        "order":  1,
        "tags":  [

                 ],
        "translations":  [
                             {
                                 "lang":  "ru",
                                 "description":  "# # BITACO GREEN TEA  # BITACO GREEN TEA  **1. Классификация и Происхождение:**  *   **Тип:** Зеленый чай. *   **Категория:** Органический чай (сертифицирован EcoCert, UTZ). *   **Происхождение:** Колумбия, регион Битако, департамент Валье-дель-Каука. Выращен и произведен компанией Agricola Himalaya S.A. на единственной коммерческой чайной плантации в Колумбии, расположенной на западном склоне Андских гор.  **2. История и Культурное Значение:**  *   **История:** Чайная плантация была основана в ",
                                 "name":  "bitaco-green-tea",
                                 "seoName":  "bitaco-green-tea"
                             }
                         ],
        "specs":  [
                      {
                          "option":  "SPEC-TYPE-GREEN",
                          "type":  "Option",
                          "showOnPage":  true,
                          "attribute":  "SPEC-TEA-TYPE",
                          "order":  1
                      }
                  ],
        "code":  "TEA-COL-BITACOGREENT",
        "catalog":  "CATALOG-AMERICAS",
        "origins":  [

                    ]
    },
    {
        "sku":  "SKU-314543",
        "published":  true,
        "order":  1,
        "tags":  [

                 ],
        "translations":  [
                             {
                                 "lang":  "ru",
                                 "description":  "# # Bitaco Leafy Black  # Bitaco Leafy Black  **1. Классификация и Происхождение:**  *   **Тип:** Ортодоксальный черный чай полной ферментации. *   **Категория:** Высокогорный органический чай. *   **Происхождение:** Колумбия, регион Ла-Кумбре, долина Валье-дель-Каука, Западные Анды. Выращивается на плантации Bitaco Tea Estate компании Agricola Himalaya S.A. *   **Географические координаты:** Плантации расположены вблизи экватора, в биосферном резервате на высоте 1800–2050 метров над уровнем мор",
                                 "name":  "bitaco-leafy-black",
                                 "seoName":  "bitaco-leafy-black"
                             }
                         ],
        "specs":  [
                      {
                          "option":  "SPEC-TYPE-GREEN",
                          "type":  "Option",
                          "showOnPage":  true,
                          "attribute":  "SPEC-TEA-TYPE",
                          "order":  1
                      }
                  ],
        "code":  "TEA-COL-BITACOLEAFYB",
        "catalog":  "CATALOG-AMERICAS",
        "origins":  [

                    ]
    },
    {
        "sku":  "SKU-708382",
        "published":  true,
        "order":  1,
        "tags":  [

                 ],
        "translations":  [
                             {
                                 "lang":  "ru",
                                 "description":  "# # Bitaco Tippy Black (Колумбийский чёрный типусовый чай)  # Bitaco Tippy Black (Колумбийский чёрный типусовый чай)  **1. Классификация и Происхождение:**  *   **Тип:** Чёрный чай (полностью ферментированный). *   **Категория:** Высокогорный органический чай, типусовый чай (содержит большое количество почек). *   **Происхождение:** Колумбия, департамент Валье-дель-Каука, регион Ла-Кумбре. Производится компанией Agricola Himalayas S.A. *   **Сертификация:** Имеет органические сертификаты USDA Or",
                                 "name":  "bitaco-tippy-black",
                                 "seoName":  "bitaco-tippy-black"
                             }
                         ],
        "specs":  [
                      {
                          "option":  "SPEC-TYPE-GREEN",
                          "type":  "Option",
                          "showOnPage":  true,
                          "attribute":  "SPEC-TEA-TYPE",
                          "order":  1
                      }
                  ],
        "code":  "TEA-COL-BITACOTIPPYB",
        "catalog":  "CATALOG-AMERICAS",
        "origins":  [

                    ]
    }
]
